airconditioner_webthing/__init__.py
airconditioner_webthing/airconditioner.py
airconditioner_webthing/airconditioner_webthing.py
airconditioner_webthing/app.py
airconditioner_webthing-0.1.5.dist-info/LICENSE
airconditioner_webthing-0.1.5.dist-info/METADATA
airconditioner_webthing-0.1.5.dist-info/WHEEL
airconditioner_webthing-0.1.5.dist-info/entry_points.txt
airconditioner_webthing-0.1.5.dist-info/top_level.txt
airconditioner_webthing-0.1.5.dist-info/RECORD
