Metadata-Version: 2.1
Name: airconditioner-webthing
Version: 0.1.5
Summary: Air conditioner WebThing
Author: Gregor Roth
Author-email: gregor.roth@web.de
Requires-Python: >=3.8
License-File: LICENSE
Requires-Dist: requests
Requires-Dist: webthing (>=0.15.0)
Requires-Dist: msmart (==0.2.5)
Requires-Dist: importlib-metadata
